lowball_ad_auth_provider/__init__.py
lowball_ad_auth_provider/auth_provider.py
tests/__init__.py
tests/conftest.py
tests/test_lowball_ad_auth_provider/__init__.py
tests/test_lowball_ad_auth_provider/conftest.py
tests/test_lowball_ad_auth_provider/test_auth_provider.py
lowball_ad_auth_provider-1.0.0.dist-info/LICENSE
lowball_ad_auth_provider-1.0.0.dist-info/METADATA
lowball_ad_auth_provider-1.0.0.dist-info/WHEEL
lowball_ad_auth_provider-1.0.0.dist-info/top_level.txt
lowball_ad_auth_provider-1.0.0.dist-info/RECORD
